hamilton/__init__.py
hamilton/contribute.py
hamilton/contrib/__init__.py
hamilton/contrib/version.py
hamilton/contrib/dagworks/__init__.py
hamilton/contrib/dagworks/text_summarization/__init__.py
hamilton/contrib/dagworks/translate_to_hamilton/__init__.py
hamilton/contrib/dagworks/translate_to_hamilton/test.py
hamilton/contrib/user/__init__.py
hamilton/contrib/user/elijahbenizzy/__init__.py
hamilton/contrib/user/elijahbenizzy/caption_images/__init__.py
hamilton/contrib/user/elijahbenizzy/convert_images_s3/__init__.py
hamilton/contrib/user/elijahbenizzy/generate_images/__init__.py
hamilton/contrib/user/elijahbenizzy/parallel_load_dataframes_s3/__init__.py
hamilton/contrib/user/example_dataflow_template/__init__.py
hamilton/contrib/user/example_dataflow_template/dataflow_template/__init__.py
hamilton/contrib/user/skrawcz/__init__.py
hamilton/contrib/user/skrawcz/air_quality_analysis/__init__.py
hamilton/contrib/user/skrawcz/customize_embeddings/__init__.py
hamilton/contrib/user/skrawcz/fine_tuning/__init__.py
hamilton/contrib/user/skrawcz/hello_world/__init__.py
hamilton/contrib/user/zilto/__init__.py
hamilton/contrib/user/zilto/lancedb_vdb/__init__.py
hamilton/contrib/user/zilto/nixtla_mlforecast/__init__.py
hamilton/contrib/user/zilto/nixtla_statsforecast/__init__.py
hamilton/contrib/user/zilto/text_summarization/__init__.py
hamilton/contrib/user/zilto/webscraper/__init__.py
hamilton/contrib/user/zilto/xgboost_optuna/__init__.py
sf_hamilton_contrib-0.0.7.dist-info/METADATA
sf_hamilton_contrib-0.0.7.dist-info/WHEEL
sf_hamilton_contrib-0.0.7.dist-info/entry_points.txt
sf_hamilton_contrib-0.0.7.dist-info/top_level.txt
sf_hamilton_contrib-0.0.7.dist-info/RECORD
