Metadata-Version: 2.1
Name: sf-hamilton-contrib
Version: 0.0.7
Summary: Hamilton's user contributed shared dataflow library.
Home-page: https://github.com/dagworks-inc/hamilton/contrib
Author: Stefan Krawczyk, Elijah ben Izzy
Author-email: stefan@dagworks.io,elijah@dagworks.io
Project-URL: Bug Reports, https://github.com/dagworks-inc/hamilton/issues
Project-URL: Source, https://github.com/dagworks-inc/hamilton/contrib
Keywords: hamilton,collaborative,shared,dataflow,library,contrib
Classifier: Development Status :: 5 - Production/Stable
Classifier: Intended Audience :: Developers
Classifier: Natural Language :: English
Classifier: License :: OSI Approved :: BSD License
Classifier: Programming Language :: Python :: 3
Classifier: Programming Language :: Python :: 3.8
Classifier: Programming Language :: Python :: 3.9
Classifier: Programming Language :: Python :: 3.10
Classifier: Programming Language :: Python :: 3.11
Classifier: Programming Language :: Python :: 3.12
Requires-Python: >=3.8, <4
Requires-Dist: sf-hamilton
Provides-Extra: contribute
Requires-Dist: click >8.0.0 ; extra == 'contribute'
Requires-Dist: gitpython ; extra == 'contribute'
Provides-Extra: visualization
Requires-Dist: sf-hamilton[visualization] ; extra == 'visualization'
